kuberesources/__init__.py
kuberesources/__main__.py
kuberesources/entities.py
kuberesources/helpers.py
kuberesources/kuberesources.py
kuberesources-1.5.1.dist-info/LICENSE
kuberesources-1.5.1.dist-info/METADATA
kuberesources-1.5.1.dist-info/WHEEL
kuberesources-1.5.1.dist-info/entry_points.txt
kuberesources-1.5.1.dist-info/top_level.txt
kuberesources-1.5.1.dist-info/RECORD
