Metadata-Version: 2.1
Name: kuberesources
Version: 1.5.1
Summary: Simple utility for getting an overview of set requests and limits in a kubernetes cluster
Home-page: https://github.com/frodehus/kuberesources
Author: Frode Hus
Author-email: frode.hus@outlook.com
License: UNKNOWN
Platform: UNKNOWN
Classifier: Programming Language :: Python :: 3
Classifier: License :: OSI Approved :: MIT License
Classifier: Operating System :: OS Independent
Requires-Python: >=3.6
Requires-Dist: kubernetes (>=11.0.0b2)
Requires-Dist: pyinquirer
Requires-Dist: prettytable
Requires-Dist: adal
Requires-Dist: colorama
